{"dependencies":[{"name":"C:\\Users\\dellpc\\Desktop\\parcel_react\\package.json","includedInParent":true,"mtime":1525691053151},{"name":"C:\\Users\\dellpc\\Desktop\\parcel_react\\.babelrc","includedInParent":true,"mtime":1521082327029},{"name":"C:\\Users\\dellpc\\Desktop\\parcel_react\\node_modules\\asn1.js\\package.json","includedInParent":true,"mtime":1521079709849},{"name":"./der","loc":{"line":3,"column":23}},{"name":"./pem","loc":{"line":4,"column":23}}],"generated":{"js":"var encoders = exports;\n\nencoders.der = require('./der');\nencoders.pem = require('./pem');\n","map":{"mappings":[{"source":"..\\node_modules\\asn1.js\\lib\\asn1\\encoders\\index.js","original":{"line":1,"column":0},"generated":{"line":1,"column":0}},{"source":"..\\node_modules\\asn1.js\\lib\\asn1\\encoders\\index.js","original":{"line":2,"column":0},"generated":{"line":2,"column":0}},{"source":"..\\node_modules\\asn1.js\\lib\\asn1\\encoders\\index.js","original":{"line":3,"column":0},"generated":{"line":3,"column":0}},{"source":"..\\node_modules\\asn1.js\\lib\\asn1\\encoders\\index.js","original":{"line":4,"column":0},"generated":{"line":4,"column":0}},{"source":"..\\node_modules\\asn1.js\\lib\\asn1\\encoders\\index.js","original":{"line":5,"column":0},"generated":{"line":5,"column":0}}],"sources":{"..\\node_modules\\asn1.js\\lib\\asn1\\encoders\\index.js":"var encoders = exports;\n\nencoders.der = require('./der');\nencoders.pem = require('./pem');\n"},"lineCount":5}},"hash":"ec430bacccd8823f91a94c2b82374579","cacheData":{"env":{}}}